fprime_native_images/__init__.py
fprime_native_images/__main__.py
fprime_native_images/package.py
fprime_native_images/templates/__main__.py.j2
fprime_native_images/templates/pyproject.toml.meta.j2
fprime_native_images/templates/pyproject.toml.tool.j2
fprime_native_images-0.2.5.dist-info/LICENSE
fprime_native_images-0.2.5.dist-info/METADATA
fprime_native_images-0.2.5.dist-info/WHEEL
fprime_native_images-0.2.5.dist-info/entry_points.txt
fprime_native_images-0.2.5.dist-info/top_level.txt
fprime_native_images-0.2.5.dist-info/RECORD
